ProjectUtility/__init__.py
ProjectUtility/_modidx.py
ProjectUtility/core.py
ProjectUtility/correlation_utilities.py
ProjectUtility/diff_expr.py
ProjectUtility/dim_red_utility.py
ProjectUtility/mis_val_utility.py
ProjectUtility-0.0.2.dist-info/LICENSE
ProjectUtility-0.0.2.dist-info/METADATA
ProjectUtility-0.0.2.dist-info/WHEEL
ProjectUtility-0.0.2.dist-info/entry_points.txt
ProjectUtility-0.0.2.dist-info/top_level.txt
ProjectUtility-0.0.2.dist-info/RECORD
